bssource/__init__.py
bssource/bssource.py
bssource/calc.py
python_bestsource-1.2.0.dist-info/LICENSE
python_bestsource-1.2.0.dist-info/METADATA
python_bestsource-1.2.0.dist-info/WHEEL
python_bestsource-1.2.0.dist-info/top_level.txt
python_bestsource-1.2.0.dist-info/RECORD
