Metadata-Version: 2.1
Name: python-bestsource
Version: 1.2.0
Summary: Python helpers to manipulate video from vapoursynth
Home-page: http://github.com/sosie-js/python-bestsource
Author: sosie-js
Author-email: sosie@sos-productions.com
License: GPL
Keywords: vapoursynth python bestsource helper
Platform: UNKNOWN
Classifier: Development Status :: 4 - Beta
Classifier: Intended Audience :: Developers
Classifier: Operating System :: OS Independent
Classifier: Programming Language :: Python :: 3
Classifier: Topic :: Multimedia :: Graphics :: Presentation
Classifier: Topic :: Software Development :: Libraries
Requires-Python: >=3.10
License-File: LICENSE
Requires-Dist: setuptools
